natedhaliwal/__init__.py
natedhaliwal/example.py
natedhaliwal-1.3.2.dist-info/LICENSE.md
natedhaliwal-1.3.2.dist-info/METADATA
natedhaliwal-1.3.2.dist-info/WHEEL
natedhaliwal-1.3.2.dist-info/RECORD
