Metadata-Version: 2.1
Name: natedhaliwal
Version: 1.3.2
Summary: A simple package to help code Python easier. Long functions with difficult parameters? Shortened!
Home-page: https://github.com/NateDhaliwal/NateDhaliwal-Package
License: MIT
Author: Nate Dhaliwal
Author-email: nathaniel.shaan@gmail.com
Requires-Python: >=3.7,<4.0
Classifier: Development Status :: 5 - Production/Stable
Classifier: Environment :: Console
Classifier: Intended Audience :: Developers
Classifier: License :: OSI Approved :: MIT License
Classifier: Natural Language :: English
Classifier: Operating System :: OS Independent
Classifier: Programming Language :: Python :: 3
Classifier: Programming Language :: Python :: 3.7
Classifier: Programming Language :: Python :: 3.8
Classifier: Programming Language :: Python :: 3.9
Classifier: Programming Language :: Python :: 3.10
Classifier: Programming Language :: Python :: 3.11
Requires-Dist: requests (>=2.31.0,<3.0.0)
Project-URL: Bug Tracker, https://github.com/NateDhaliwal/NateDhaliwal-Package/issues
Project-URL: Repository, https://github.com/NateDhaliwal/NateDhaliwal-Package
Project-URL: Replit, https://replit.com/@NateDhaliwal/natedhaliwalpackage
